{
    "figuras": [
        {
            "Nombre": "Letra-A",
            "Drones": [
                {
                    "ID": 1,
                    "POS": "5,4"
                },
                {
                    "ID": 2,
                    "POS": "6,4"
                },
                {
                    "ID": 3,
                    "POS": "7,4"
                },
                {
                    "ID": 4,
                    "POS": "5,5"
                },
                {
                    "ID": 5,
                    "POS": "7,5"
                },
                {
                    "ID": 6,
                    "POS": "5,6"
                },
                {
                    "ID": 7,
                    "POS": "6,6"
                },
                {
                    "ID": 8,
                    "POS": "7,6"
                },
                {
                    "ID": 9,
                    "POS": "5,7"
                },
                {
                    "ID": 10,
                    "POS": "7,7"
                }
            ]
        }
    ]
}